{
  "run_id": "3cb7aecd",
  "spec": "raw-ingest-bea-rpp",
  "executed_at": "2026-04-10T22:40:04.891558+00:00",
  "rules_total": 19,
  "rules_passed": 17,
  "rules_failed": 2,
  "rules_errored": 0,
  "p0_passed": false,
  "results": [
    {
      "rule_id": "RAW-BEA-001",
      "spec": "raw-ingest-bea-rpp",
      "category": null,
      "passed": false,
      "raw_value": 1,
      "threshold": "result = 0",
      "detail": "actual=1.0, threshold=result = 0.0",
      "violations": 1,
      "execution_time_ms": 0,
      "error": null,
      "executed_at": "2026-04-10T22:40:04.876308+00:00"
    },
    {
      "rule_id": "RAW-BEA-002",
      "spec": "raw-ingest-bea-rpp",
      "category": null,
      "passed": true,
      "raw_value": 0,
      "threshold": "result_count = 0",
      "detail": "actual=0, threshold=result_count = 0.0",
      "violations": 0,
      "execution_time_ms": 0,
      "error": null,
      "executed_at": "2026-04-10T22:40:04.877159+00:00"
    },
    {
      "rule_id": "RAW-BEA-003",
      "spec": "raw-ingest-bea-rpp",
      "category": null,
      "passed": true,
      "raw_value": 0,
      "threshold": "result_count = 0",
      "detail": "actual=0, threshold=result_count = 0.0",
      "violations": 0,
      "execution_time_ms": 0,
      "error": null,
      "executed_at": "2026-04-10T22:40:04.878161+00:00"
    },
    {
      "rule_id": "RAW-BEA-004",
      "spec": "raw-ingest-bea-rpp",
      "category": null,
      "passed": true,
      "raw_value": 0,
      "threshold": "result_count = 0",
      "detail": "actual=0, threshold=result_count = 0.0",
      "violations": 0,
      "execution_time_ms": 0,
      "error": null,
      "executed_at": "2026-04-10T22:40:04.879071+00:00"
    },
    {
      "rule_id": "RAW-BEA-005",
      "spec": "raw-ingest-bea-rpp",
      "category": null,
      "passed": true,
      "raw_value": 0,
      "threshold": "result_count = 0",
      "detail": "actual=0, threshold=result_count = 0.0",
      "violations": 0,
      "execution_time_ms": 0,
      "error": null,
      "executed_at": "2026-04-10T22:40:04.879990+00:00"
    },
    {
      "rule_id": "RAW-BEA-006",
      "spec": "raw-ingest-bea-rpp",
      "category": null,
      "passed": true,
      "raw_value": 0,
      "threshold": "result_count = 0",
      "detail": "actual=0, threshold=result_count = 0.0",
      "violations": 0,
      "execution_time_ms": 0,
      "error": null,
      "executed_at": "2026-04-10T22:40:04.880779+00:00"
    },
    {
      "rule_id": "RAW-BEA-007",
      "spec": "raw-ingest-bea-rpp",
      "category": null,
      "passed": true,
      "raw_value": 0,
      "threshold": "result_count = 0",
      "detail": "actual=0, threshold=result_count = 0.0",
      "violations": 0,
      "execution_time_ms": 0,
      "error": null,
      "executed_at": "2026-04-10T22:40:04.881704+00:00"
    },
    {
      "rule_id": "RAW-BEA-008",
      "spec": "raw-ingest-bea-rpp",
      "category": null,
      "passed": true,
      "raw_value": 0,
      "threshold": "result_count = 0",
      "detail": "actual=0, threshold=result_count = 0.0",
      "violations": 0,
      "execution_time_ms": 0,
      "error": null,
      "executed_at": "2026-04-10T22:40:04.882668+00:00"
    },
    {
      "rule_id": "RAW-BEA-009",
      "spec": "raw-ingest-bea-rpp",
      "category": null,
      "passed": true,
      "raw_value": 0,
      "threshold": "result = 0",
      "detail": "actual=0.0, threshold=result = 0.0",
      "violations": 0,
      "execution_time_ms": 0,
      "error": null,
      "executed_at": "2026-04-10T22:40:04.883569+00:00"
    },
    {
      "rule_id": "RAW-BEA-010",
      "spec": "raw-ingest-bea-rpp",
      "category": null,
      "passed": false,
      "raw_value": 1,
      "threshold": "result = 0",
      "detail": "actual=1.0, threshold=result = 0.0",
      "violations": 1,
      "execution_time_ms": 1,
      "error": null,
      "executed_at": "2026-04-10T22:40:04.884972+00:00"
    },
    {
      "rule_id": "RAW-BEA-011",
      "spec": "raw-ingest-bea-rpp",
      "category": null,
      "passed": true,
      "raw_value": 0,
      "threshold": "result_count = 0",
      "detail": "actual=0, threshold=result_count = 0.0",
      "violations": 0,
      "execution_time_ms": 0,
      "error": null,
      "executed_at": "2026-04-10T22:40:04.885517+00:00"
    },
    {
      "rule_id": "RAW-BEA-012",
      "spec": "raw-ingest-bea-rpp",
      "category": null,
      "passed": true,
      "raw_value": 0,
      "threshold": "result_count = 0",
      "detail": "actual=0, threshold=result_count = 0.0",
      "violations": 0,
      "execution_time_ms": 0,
      "error": null,
      "executed_at": "2026-04-10T22:40:04.886418+00:00"
    },
    {
      "rule_id": "RAW-BEA-013",
      "spec": "raw-ingest-bea-rpp",
      "category": null,
      "passed": true,
      "raw_value": 0,
      "threshold": "result_count = 0",
      "detail": "actual=0, threshold=result_count = 0.0",
      "violations": 0,
      "execution_time_ms": 0,
      "error": null,
      "executed_at": "2026-04-10T22:40:04.887191+00:00"
    },
    {
      "rule_id": "RAW-BEA-014",
      "spec": "raw-ingest-bea-rpp",
      "category": null,
      "passed": true,
      "raw_value": 0,
      "threshold": "result_count = 0",
      "detail": "actual=0, threshold=result_count = 0.0",
      "violations": 0,
      "execution_time_ms": 0,
      "error": null,
      "executed_at": "2026-04-10T22:40:04.888015+00:00"
    },
    {
      "rule_id": "RAW-BEA-015",
      "spec": "raw-ingest-bea-rpp",
      "category": null,
      "passed": true,
      "raw_value": 0,
      "threshold": "result_count = 0",
      "detail": "actual=0, threshold=result_count = 0.0",
      "violations": 0,
      "execution_time_ms": 0,
      "error": null,
      "executed_at": "2026-04-10T22:40:04.888825+00:00"
    },
    {
      "rule_id": "RAW-BEA-016",
      "spec": "raw-ingest-bea-rpp",
      "category": null,
      "passed": true,
      "raw_value": 0,
      "threshold": "result_count = 0",
      "detail": "actual=0, threshold=result_count = 0.0",
      "violations": 0,
      "execution_time_ms": 0,
      "error": null,
      "executed_at": "2026-04-10T22:40:04.889556+00:00"
    },
    {
      "rule_id": "RAW-BEA-017",
      "spec": "raw-ingest-bea-rpp",
      "category": null,
      "passed": true,
      "raw_value": 0,
      "threshold": "result = 0",
      "detail": "actual=0.0, threshold=result = 0.0",
      "violations": 0,
      "execution_time_ms": 0,
      "error": null,
      "executed_at": "2026-04-10T22:40:04.890090+00:00"
    },
    {
      "rule_id": "RAW-BEA-018",
      "spec": "raw-ingest-bea-rpp",
      "category": null,
      "passed": true,
      "raw_value": 0,
      "threshold": "result = 0",
      "detail": "actual=0.0, threshold=result = 0.0",
      "violations": 0,
      "execution_time_ms": 0,
      "error": null,
      "executed_at": "2026-04-10T22:40:04.890614+00:00"
    },
    {
      "rule_id": "RAW-BEA-019",
      "spec": "raw-ingest-bea-rpp",
      "category": null,
      "passed": true,
      "raw_value": 0,
      "threshold": "result = 0",
      "detail": "actual=0.0, threshold=result = 0.0",
      "violations": 0,
      "execution_time_ms": 0,
      "error": null,
      "executed_at": "2026-04-10T22:40:04.891147+00:00"
    }
  ]
}
